propersandwich/__init__.py
propersandwich/googlesheet.py
propersandwich/postgres.py
propersandwich-0.1.10.dist-info/LICENSE
propersandwich-0.1.10.dist-info/METADATA
propersandwich-0.1.10.dist-info/WHEEL
propersandwich-0.1.10.dist-info/top_level.txt
propersandwich-0.1.10.dist-info/RECORD
