Metadata-Version: 2.1
Name: propersandwich
Version: 0.1.10
Summary: propersandwich package
Home-page: https://github.com/senseibara/propersandwich
Author: Senseibara
Author-email: ndiayebara93@gmail.com
License: MIT License        
License-File: LICENSE
Requires-Dist: pandas
Requires-Dist: python-dotenv
Requires-Dist: pygsheets
Requires-Dist: psycopg2-binary
